README.rst
setup.py
swagger_validator/__init__.py
swagger_validator/core.py
swagger_validator/five.py
swagger_validator.egg-info/PKG-INFO
swagger_validator.egg-info/SOURCES.txt
swagger_validator.egg-info/dependency_links.txt
swagger_validator.egg-info/requires.txt
swagger_validator.egg-info/top_level.txt